ConfigModel_MCMC/ConfigModel_MCMC.py
ConfigModel_MCMC/__init__.py
ConfigModel_MCMC-0.2.dist-info/LICENSE
ConfigModel_MCMC-0.2.dist-info/METADATA
ConfigModel_MCMC-0.2.dist-info/WHEEL
ConfigModel_MCMC-0.2.dist-info/top_level.txt
ConfigModel_MCMC-0.2.dist-info/RECORD
