Metadata-Version: 2.1
Name: ConfigModel_MCMC
Version: 0.2
Summary: A tool for sampling networks from the Configuration model
Home-page: https://arxiv.org/abs/2105.12120
Author: Upasana Dutta; Bailey K. Fosdick; Aaron Clauset
Author-email: upasana.dutta@colorado.edu
Keywords: ConfigModel_MCMC,MCMC,Configuration model,double edge swap,degree sequence,null distribution,random graph
Classifier: Programming Language :: Python :: 3
Classifier: License :: OSI Approved :: GNU General Public License v3 or later (GPLv3+)
Classifier: Operating System :: OS Independent
Classifier: Natural Language :: English
License-File: LICENSE
Requires-Dist: numpy ==1.21.0
Requires-Dist: networkx ==3.1
Requires-Dist: scipy ==1.8.0
Requires-Dist: numba ==0.56.0
Requires-Dist: arch ==5.3.1
Requires-Dist: python-igraph ==0.11.3
Requires-Dist: tqdm ==4.62.2
